simsm/__init__.py
simsm/simsm.py
sim_sm-0.9.dist-info/LICENSE
sim_sm-0.9.dist-info/METADATA
sim_sm-0.9.dist-info/WHEEL
sim_sm-0.9.dist-info/entry_points.txt
sim_sm-0.9.dist-info/top_level.txt
sim_sm-0.9.dist-info/RECORD
