Metadata-Version: 2.1
Name: sim-sm
Version: 0.9
Summary: Linhas de ônibus do SIM-SM no seu terminal.
Home-page: https://github.com/jviriato/sim-sm/
Author: José Victor Viriato
Author-email: josevviriato@gmail.com
License: MIT
Keywords: CLI,bus,python
Platform: UNKNOWN
Classifier: Programming Language :: Python :: 3
Classifier: License :: OSI Approved :: MIT License
Classifier: Operating System :: OS Independent
Requires-Dist: terminaltables
Requires-Dist: colorama
Requires-Dist: requests
